connvitals/__init__.py
connvitals/collector.py
connvitals/config.py
connvitals/icmp.py
connvitals/ping.py
connvitals/ports.py
connvitals/traceroute.py
connvitals/utils.py
connvitals-4.3.2.dist-info/METADATA
connvitals-4.3.2.dist-info/RECORD
connvitals-4.3.2.dist-info/WHEEL
connvitals-4.3.2.dist-info/entry_points.txt
connvitals-4.3.2.dist-info/top_level.txt
